tempnetviz/__init__.py
tempnetviz/graph_animation.py
tempnetviz/listbox_selection.py
tempnetviz/main_gui.py
tempnetviz/multilayer_plot.py
tempnetviz/read_graph.py
tempnetviz/settings_window.py
tempnetviz/setup.py
tempnetviz/temporal_layout.py
tempnetviz/tooltip.py
tempnetviz-0.1.122.dist-info/entry_points.txt
tempnetviz-0.1.122.dist-info/LICENSE.txt
tempnetviz-0.1.122.dist-info/METADATA
tempnetviz-0.1.122.dist-info/WHEEL
tempnetviz-0.1.122.dist-info/RECORD
