Metadata-Version: 2.3
Name: tempnetviz
Version: 0.1.122
Summary: 
License: MIT
Author: Corentin Nelias
Requires-Python: >=3.13
Classifier: License :: OSI Approved :: MIT License
Classifier: Programming Language :: Python :: 3
Classifier: Programming Language :: Python :: 3.13
Requires-Dist: igraph (>=0.11.9,<0.12.0)
Requires-Dist: matplotlib (>=3.10.6,<4.0.0)
Requires-Dist: networkx (>=3.5,<4.0)
Requires-Dist: numpy (>=2.3.2,<3.0.0)
Requires-Dist: pandas (>=2.3.2,<3.0.0)
Requires-Dist: scipy (>=1.16.1,<2.0.0)
